findee/__init__.py
findee/_version.py
findee/findee.py
findee/util.py
findee-0.1.6.dist-info/licenses/LICENSE
findee-0.1.6.dist-info/METADATA
findee-0.1.6.dist-info/WHEEL
findee-0.1.6.dist-info/top_level.txt
findee-0.1.6.dist-info/RECORD
