Metadata-Version: 2.4
Name: findee
Version: 0.1.6
Summary: An autonomous vehicle platform by Pathfinder
Author-email: Pathfinder <finder1028@gmail.com>
License: MIT License
Project-URL: Homepage, https://github.com/Comrid/findee
Project-URL: Bug Tracker, https://github.com/Comrid/findee/issues
Keywords: pathfinder,finder,findee,raspberry-pi,robotics,autonomous-vehicle,gpio
Classifier: Development Status :: 3 - Alpha
Classifier: Intended Audience :: Developers
Classifier: Intended Audience :: Education
Classifier: Topic :: Scientific/Engineering
Classifier: Topic :: System :: Hardware
Classifier: Programming Language :: Python :: 3
Classifier: Programming Language :: Python :: 3.7
Classifier: Programming Language :: Python :: 3.8
Classifier: Programming Language :: Python :: 3.9
Classifier: Programming Language :: Python :: 3.10
Classifier: Programming Language :: Python :: 3.11
Classifier: License :: OSI Approved :: MIT License
Classifier: Operating System :: POSIX :: Linux
Requires-Python: >=3.7
License-File: LICENSE
Requires-Dist: numpy<2.0,>=1.21.0
Requires-Dist: RPi.GPIO
Requires-Dist: picamera2
Requires-Dist: opencv-python
Requires-Dist: psutil
Dynamic: license-file
